[
  {
    "id": 1,
    "kind": "입금",
    "coin_name": "BTC 비트코인",
    "blockchain_type": "ERC-20",
    "quantity": 100,
    "price": 5000,
    "status": "완료",
    "address": "asdasdasdsadqweqeqweq",
    "updated_at": "2022/02/01 12:00"
  },
  {
    "id": 2,
    "kind": "입금",
    "coin_name": "BTC 비트코인",
    "blockchain_type": "ERC-20",
    "quantity": 100,
    "price": 5000,
    "status": "완료",
    "address": "asdasdasdsadqweqeqweq",
    "updated_at": "2022/02/01 12:00"
  },
  {
    "id": 3,
    "kind": "입금",
    "coin_name": "BTC 비트코인",
    "blockchain_type": "ERC-20",
    "quantity": 100,
    "price": 5000,
    "status": "완료",
    "address": "asdasdasdsadqweqeqweq",
    "updated_at": "2022/02/01"
  },
  {
    "id": 4,
    "kind": "입금",
    "coin_name": "BTC 비트코인",
    "blockchain_type": "ERC-20",
    "quantity": 100,
    "price": 5000,
    "status": "완료",
    "address": "asdasdasdsadqweqeqweq",
    "updated_at": "2022/02/01"
  },
  {
    "id": 5,
    "kind": "입금",
    "coin_name": "BTC 비트코인",
    "blockchain_type": "ERC-20",
    "quantity": 100,
    "price": 5000,
    "status": "완료",
    "address": "asdasdasdsadqweqeqweq",
    "updated_at": "2022/02/01"
  },
  {
    "id": 6,
    "kind": "입금",
    "coin_name": "BTC 비트코인",
    "blockchain_type": "ERC-20",
    "quantity": 100,
    "price": 5000,
    "status": "완료",
    "address": "asdasdasdsadqweqeqweq",
    "updated_at": "2022/02/01"
  },
  {
    "id": 7,
    "kind": "입금",
    "coin_name": "BTC 비트코인",
    "blockchain_type": "ERC-20",
    "quantity": 100,
    "price": 5000,
    "status": "완료",
    "address": "asdasdasdsadqweqeqweq",
    "updated_at": "2022/02/01"
  },
  {
    "id": 8,
    "kind": "입금",
    "coin_name": "BTC 비트코인",
    "blockchain_type": "ERC-20",
    "quantity": 100,
    "price": 5000,
    "status": "완료",
    "address": "asdasdasdsadqweqeqweq",
    "updated_at": "2022/02/01"
  },
  {
    "id": 9,
    "kind": "입금",
    "coin_name": "BTC 비트코인",
    "blockchain_type": "ERC-20",
    "quantity": 100,
    "price": 5000,
    "status": "완료",
    "address": "asdasdasdsadqweqeqweq",
    "updated_at": "2022/02/01"
  },
  {
    "id": 10,
    "kind": "입금",
    "coin_name": "BTC 비트코인",
    "blockchain_type": "ERC-20",
    "quantity": 100,
    "price": 5000,
    "status": "완료",
    "address": "asdasdasdsadqweqeqweq",
    "updated_at": "2022/02/01"
  },
  {
    "id": 11,
    "kind": "입금",
    "coin_name": "BTC 비트코인",
    "blockchain_type": "ERC-20",
    "quantity": 100,
    "price": 5000,
    "status": "완료",
    "address": "asdasdasdsadqweqeqweq",
    "updated_at": "2022/02/01"
  },
  {
    "id": 12,
    "kind": "입금",
    "coin_name": "BTC 비트코인",
    "blockchain_type": "ERC-20",
    "quantity": 100,
    "price": 5000,
    "status": "완료",
    "address": "asdasdasdsadqweqeqweq",
    "updated_at": "2022/02/01"
  },
  {
    "id": 13,
    "kind": "입금",
    "coin_name": "BTC 비트코인",
    "blockchain_type": "ERC-20",
    "quantity": 100,
    "price": 5000,
    "status": "완료",
    "address": "asdasdasdsadqweqeqweq",
    "updated_at": "2022/02/01"
  },
  {
    "id": 14,
    "kind": "입금",
    "coin_name": "BTC 비트코인",
    "blockchain_type": "ERC-20",
    "quantity": 100,
    "price": 5000,
    "status": "완료",
    "address": "asdasdasdsadqweqeqweq",
    "updated_at": "2022/02/01"
  },
  {
    "id": 15,
    "kind": "입금",
    "coin_name": "BTC 비트코인",
    "blockchain_type": "ERC-20",
    "quantity": 100,
    "price": 5000,
    "status": "완료",
    "address": "asdasdasdsadqweqeqweq",
    "updated_at": "2022/02/01"
  },
  {
    "id": 16,
    "kind": "입금",
    "coin_name": "BTC 비트코인",
    "blockchain_type": "ERC-20",
    "quantity": 100,
    "price": 5000,
    "status": "완료",
    "address": "asdasdasdsadqweqeqweq",
    "updated_at": "2022/02/01"
  },
  {
    "id": 17,
    "kind": "입금",
    "coin_name": "BTC 비트코인",
    "blockchain_type": "ERC-20",
    "quantity": 100,
    "price": 5000,
    "status": "완료",
    "address": "asdasdasdsadqweqeqweq",
    "updated_at": "2022/02/01"
  },
  {
    "id": 18,
    "kind": "입금",
    "coin_name": "BTC 비트코인",
    "blockchain_type": "ERC-20",
    "quantity": 100,
    "price": 5000,
    "status": "완료",
    "address": "asdasdasdsadqweqeqweq",
    "updated_at": "2022/02/01"
  },
  {
    "id": 19,
    "kind": "입금",
    "coin_name": "BTC 비트코인",
    "blockchain_type": "ERC-20",
    "quantity": 100,
    "price": 5000,
    "status": "완료",
    "address": "asdasdasdsadqweqeqweq",
    "updated_at": "2022/02/01"
  },
  {
    "id": 20,
    "kind": "입금",
    "coin_name": "BTC 비트코인",
    "blockchain_type": "ERC-20",
    "quantity": 100,
    "price": 5000,
    "status": "완료",
    "address": "asdasdasdsadqweqeqweq",
    "updated_at": "2022/02/01"
  }
]
